slrun/__init__.py
slrun/cli.py
slrun/slrun.py
slrun-0.1.4.dist-info/METADATA
slrun-0.1.4.dist-info/WHEEL
slrun-0.1.4.dist-info/entry_points.txt
slrun-0.1.4.dist-info/licenses/LICENSE
slrun-0.1.4.dist-info/RECORD
