Metadata-Version: 2.4
Name: slrun
Version: 0.1.4
Summary: Run commands on SLURM as if local with seamless detach/reattach
Project-URL: Homepage, https://github.com/yashsavani/slrun
Project-URL: Bug Tracker, https://github.com/yashsavani/slrun/issues
Author-email: Yash Savani <yash.savani@gmail.com>
License: MIT
License-File: LICENSE
Keywords: cluster,hpc,scheduler,slurm
Classifier: Development Status :: 4 - Beta
Classifier: Intended Audience :: Science/Research
Classifier: License :: OSI Approved :: MIT License
Classifier: Operating System :: POSIX :: Linux
Classifier: Programming Language :: Python :: 3
Classifier: Topic :: System :: Clustering
Requires-Python: >=3.6
Requires-Dist: toml>=0.10.0
